pair_learning/__init__.py
pair_learning/losses/__init__.py
pair_learning/losses/adaptive_softmax_loss.py
pair_learning/losses/base_loss.py
pair_learning/losses/contrastive_loss.py
pair_learning/losses/margin_softmax_loss.py
pair_learning/losses/pairwise_softmax_loss.py
pair_learning/losses/triplet_loss.py
pair_learning/miners/__init__.py
pair_learning/miners/base_miner.py
pair_learning/miners/distance_miner.py
pair_learning/miners/hard_triplet_miner.py
pair_learning/miners/pairwise_miner.py
pair_learning/reducers/__init__.py
pair_learning/reducers/base_reducer.py
pair_learning/reducers/mean_non_zero_reducer.py
pair_learning/reducers/mean_reducer.py
pair_learning/reducers/threshold_reducer.py
pair_learning/utils/__init__.py
pair_learning/utils/common_function.py
pair_learning-0.1.2.dist-info/LICENSE
pair_learning-0.1.2.dist-info/METADATA
pair_learning-0.1.2.dist-info/WHEEL
pair_learning-0.1.2.dist-info/top_level.txt
pair_learning-0.1.2.dist-info/RECORD
