Metadata-Version: 2.1
Name: pair-learning
Version: 0.1.2
Summary: The easiest way to use deep metric learning for pair data. Written in PyTorch.
Home-page: https://github.com/rikiyasuzuki/pair_learning
Author: Rikiya Suzuki
Author-email: rikiyasuzuki1112@gmail.com
License: UNKNOWN
Keywords: metric_learning,torch
Platform: UNKNOWN
Classifier: License :: OSI Approved :: MIT License
Classifier: Programming Language :: Python :: 3
Requires-Python: >=3.0
Requires-Dist: numpy
Requires-Dist: torch
